electrolytes/__init__.py
electrolytes/__main__.py
electrolytes/db1.json
electrolytes/py.typed
electrolytes-0.4.8.dist-info/licenses/LICENSE.txt
electrolytes-0.4.8.dist-info/WHEEL
electrolytes-0.4.8.dist-info/entry_points.txt
electrolytes-0.4.8.dist-info/METADATA
electrolytes-0.4.8.dist-info/RECORD
