Metadata-Version: 2.4
Name: electrolytes
Version: 0.4.8
Summary: Electrolyte database manager
Author: Gabriel S. Gerlero
Author-email: Gabriel S. Gerlero <ggerlero@cimec.unl.edu.ar>
License-Expression: GPL-3.0-only
License-File: LICENSE.txt
Classifier: Development Status :: 4 - Beta
Classifier: Environment :: Console
Classifier: Framework :: Pydantic :: 2
Classifier: Intended Audience :: Science/Research
Classifier: Intended Audience :: Developers
Classifier: License :: OSI Approved :: GNU General Public License v3 (GPLv3)
Classifier: Operating System :: OS Independent
Classifier: Programming Language :: Python :: 3 :: Only
Classifier: Programming Language :: Python :: 3.10
Classifier: Programming Language :: Python :: 3.11
Classifier: Programming Language :: Python :: 3.12
Classifier: Programming Language :: Python :: 3.13
Classifier: Topic :: Scientific/Engineering :: Chemistry
Classifier: Topic :: Scientific/Engineering :: Physics
Classifier: Topic :: Software Development :: Libraries :: Python Modules
Classifier: Topic :: Utilities
Classifier: Typing :: Typed
Requires-Dist: typer-slim>=0.12.0,<0.17
Requires-Dist: pydantic>=2.0.3,<3
Requires-Dist: filelock>=3.12.3,<4
Requires-Dist: typing-extensions>=4,<5 ; python_full_version < '3.11'
Requires-Python: >=3.10
Project-URL: Homepage, https://github.com/microfluidica/electrolytes
Project-URL: Repository, https://github.com/microfluidica/electrolytes
